tensorfont/__init__.py
tensorfont/dataset.py
tensorfont/generators.py
tensorfont/getKerningPairsFromOTF.py
tensorfont/interpshape.py
tensorfont-0.1.0.dist-info/METADATA
tensorfont-0.1.0.dist-info/WHEEL
tensorfont-0.1.0.dist-info/top_level.txt
tensorfont-0.1.0.dist-info/RECORD
