Metadata-Version: 2.1
Name: tensorfont
Version: 0.1.0
Summary: Turn font glyphs into numpy arrays
Home-page: https://github.com/simoncozens/tensorfont
Author: Simon Cozens
Author-email: simon@simon-cozens.org
License: MIT
Platform: UNKNOWN
Classifier: Programming Language :: Python
Classifier: Programming Language :: Python :: 2
Classifier: Programming Language :: Python :: 3
Classifier: License :: OSI Approved :: MIT License
Classifier: Development Status :: 4 - Beta
Requires-Dist: scikit-image
Requires-Dist: numpy
Requires-Dist: freetype-py
Requires-Dist: scipy
Requires-Dist: uharfbuzz
Requires-Dist: fonttools
